main.py
setup.py
rl_vm_scheduling.egg-info/PKG-INFO
rl_vm_scheduling.egg-info/SOURCES.txt
rl_vm_scheduling.egg-info/dependency_links.txt
rl_vm_scheduling.egg-info/requires.txt
rl_vm_scheduling.egg-info/top_level.txt